[{"timestamp": 1757511000, "gmtoffset": 0, "datetime": "2025-09-10 13:30:00", "open": 10.5, "high": 10.555, "low": 10.46, "close": 10.505, "volume": 37494}, {"timestamp": 1757514600, "gmtoffset": 0, "datetime": "2025-09-10 14:30:00", "open": 10.489999, "high": 10.489999, "low": 10.454999, "close": 10.46, "volume": 34918}, {"timestamp": 1757518200, "gmtoffset": 0, "datetime": "2025-09-10 15:30:00", "open": 10.461, "high": 10.4699, "low": 10.43, "close": 10.4392, "volume": 35661}, {"timestamp": 1757521800, "gmtoffset": 0, "datetime": "2025-09-10 16:30:00", "open": 10.439999, "high": 10.439999, "low": 10.414999, "close": 10.414999, "volume": 24844}, {"timestamp": 1757525400, "gmtoffset": 0, "datetime": "2025-09-10 17:30:00", "open": 10.418999, "high": 10.444999, "low": 10.418999, "close": 10.439999, "volume": 32137}, {"timestamp": 1757529000, "gmtoffset": 0, "datetime": "2025-09-10 18:30:00", "open": 10.439999, "high": 10.489999, "low": 10.439999, "close": 10.465, "volume": 76930}, {"timestamp": 1757532600, "gmtoffset": 0, "datetime": "2025-09-10 19:30:00", "open": 10.465, "high": 10.484999, "low": 10.449899, "close": 10.465, "volume": 50501}, {"timestamp": 1757534400, "gmtoffset": 0, "datetime": "2025-09-10 20:00:00", "open": 10.47, "high": 10.47, "low": 10.47, "close": 10.47, "volume": null}, {"timestamp": 1757597400, "gmtoffset": 0, "datetime": "2025-09-11 13:30:00", "open": 10.5, "high": 10.539999, "low": 10.46, "close": 10.4665, "volume": 31052}, {"timestamp": 1757601000, "gmtoffset": 0, "datetime": "2025-09-11 14:30:00", "open": 10.465, "high": 10.52, "low": 10.43, "close": 10.52, "volume": 57661}, {"timestamp": 1757604600, "gmtoffset": 0, "datetime": "2025-09-11 15:30:00", "open": 10.524299, "high": 10.529999, "low": 10.489999, "close": 10.524999, "volume": 66561}, {"timestamp": 1757608200, "gmtoffset": 0, "datetime": "2025-09-11 16:30:00", "open": 10.520999, "high": 10.524999, "low": 10.499899, "close": 10.5, "volume": 43220}, {"timestamp": 1757611800, "gmtoffset": 0, "datetime": "2025-09-11 17:30:00", "open": 10.5, "high": 10.52, "low": 10.444999, "close": 10.465, "volume": 81125}, {"timestamp": 1757615400, "gmtoffset": 0, "datetime": "2025-09-11 18:30:00", "open": 10.459799, "high": 10.529999, "low": 10.459799, "close": 10.524999, "volume": 86044}, {"timestamp": 1757619000, "gmtoffset": 0, "datetime": "2025-09-11 19:30:00", "open": 10.524999, "high": 10.539999, "low": 10.51, "close": 10.51, "volume": 41294}, {"timestamp": 1757620800, "gmtoffset": 0, "datetime": "2025-09-11 20:00:00", "open": 10.51, "high": 10.51, "low": 10.51, "close": 10.51, "volume": null}, {"timestamp": 1757683800, "gmtoffset": 0, "datetime": "2025-09-12 13:30:00", "open": 10.479999, "high": 10.543, "low": 10.449999, "close": 10.475, "volume": 44436}, {"timestamp": 1757687400, "gmtoffset": 0, "datetime": "2025-09-12 14:30:00", "open": 10.478899, "high": 10.484999, "low": 10.4593, "close": 10.465, "volume": 63400}, {"timestamp": 1757691000, "gmtoffset": 0, "datetime": "2025-09-12 15:30:00", "open": 10.468999, "high": 10.489999, "low": 10.439999, "close": 10.4875, "volume": 57593}, {"timestamp": 1757694600, "gmtoffset": 0, "datetime": "2025-09-12 16:30:00", "open": 10.484999, "high": 10.489999, "low": 10.454999, "close": 10.4645, "volume": 25146}, {"timestamp": 1757698200, "gmtoffset": 0, "datetime": "2025-09-12 17:30:00", "open": 10.46, "high": 10.465, "low": 10.440099, "close": 10.449999, "volume": 24645}, {"timestamp": 1757701800, "gmtoffset": 0, "datetime": "2025-09-12 18:30:00", "open": 10.454999, "high": 10.47, "low": 10.435, "close": 10.435, "volume": 41063}, {"timestamp": 1757705400, "gmtoffset": 0, "datetime": "2025-09-12 19:30:00", "open": 10.435, "high": 10.5, "low": 10.43, "close": 10.479999, "volume": 108620}, {"timestamp": 1757707200, "gmtoffset": 0, "datetime": "2025-09-12 20:00:00", "open": 10.47, "high": 10.47, "low": 10.47, "close": 10.47, "volume": null}, {"timestamp": 1757943000, "gmtoffset": 0, "datetime": "2025-09-15 13:30:00", "open": 10.21, "high": 10.22, "low": 9.979999, "close": 10.104999, "volume": 610014}, {"timestamp": 1757946600, "gmtoffset": 0, "datetime": "2025-09-15 14:30:00", "open": 10.109999, "high": 10.14, "low": 10.029999, "close": 10.0691, "volume": 289412}, {"timestamp": 1757950200, "gmtoffset": 0, "datetime": "2025-09-15 15:30:00", "open": 10.064999, "high": 10.085, "low": 10.024999, "close": 10.034999, "volume": 153800}, {"timestamp": 1757953800, "gmtoffset": 0, "datetime": "2025-09-15 16:30:00", "open": 10.029999, "high": 10.045, "low": 9.979999, "close": 9.9881, "volume": 247077}, {"timestamp": 1757957400, "gmtoffset": 0, "datetime": "2025-09-15 17:30:00", "open": 9.984999, "high": 10.01, "low": 9.909999, "close": 9.994999, "volume": 234762}, {"timestamp": 1757961000, "gmtoffset": 0, "datetime": "2025-09-15 18:30:00", "open": 9.994999, "high": 10.039999, "low": 9.96, "close": 9.965, "volume": 263504}, {"timestamp": 1757964600, "gmtoffset": 0, "datetime": "2025-09-15 19:30:00", "open": 9.96, "high": 9.97, "low": 9.909999, "close": 9.93, "volume": 279937}, {"timestamp": 1757966400, "gmtoffset": 0, "datetime": "2025-09-15 20:00:00", "open": 9.92, "high": 9.92, "low": 9.92, "close": 9.92, "volume": null}]